bmlt_client/__init__.py
bmlt_client/api_client.py
bmlt_client/api_response.py
bmlt_client/configuration.py
bmlt_client/exceptions.py
bmlt_client/py.typed
bmlt_client/rest.py
bmlt_client/api/__init__.py
bmlt_client/api/root_server_api.py
bmlt_client/models/__init__.py
bmlt_client/models/authentication_error.py
bmlt_client/models/authorization_error.py
bmlt_client/models/conflict_error.py
bmlt_client/models/error_test.py
bmlt_client/models/format.py
bmlt_client/models/format_base.py
bmlt_client/models/format_create.py
bmlt_client/models/format_partial_update.py
bmlt_client/models/format_translation.py
bmlt_client/models/format_update.py
bmlt_client/models/meeting.py
bmlt_client/models/meeting_base.py
bmlt_client/models/meeting_change_resource.py
bmlt_client/models/meeting_create.py
bmlt_client/models/meeting_partial_update.py
bmlt_client/models/meeting_update.py
bmlt_client/models/not_found_error.py
bmlt_client/models/root_server.py
bmlt_client/models/root_server_base.py
bmlt_client/models/root_server_base_statistics.py
bmlt_client/models/root_server_base_statistics_meetings.py
bmlt_client/models/root_server_base_statistics_service_bodies.py
bmlt_client/models/server_error.py
bmlt_client/models/service_body.py
bmlt_client/models/service_body_base.py
bmlt_client/models/service_body_create.py
bmlt_client/models/service_body_partial_update.py
bmlt_client/models/service_body_update.py
bmlt_client/models/token.py
bmlt_client/models/token_credentials.py
bmlt_client/models/user.py
bmlt_client/models/user_base.py
bmlt_client/models/user_create.py
bmlt_client/models/user_partial_update.py
bmlt_client/models/user_update.py
bmlt_client/models/validation_error.py
bmlt_client-1.0.0.dist-info/METADATA
bmlt_client-1.0.0.dist-info/WHEEL
bmlt_client-1.0.0.dist-info/top_level.txt
bmlt_client-1.0.0.dist-info/RECORD
