Metadata-Version: 2.4
Name: bmlt_client
Version: 1.0.0
Summary: BMLT
Home-page: 
Author: OpenAPI Generator community
Author-email: OpenAPI Generator Community <team@openapitools.org>
License-Expression: MIT
Project-URL: Repository, https://github.com/bmlt-enabled/bmlt-server-python-client
Keywords: OpenAPI,OpenAPI-Generator,BMLT
Requires-Python: >=3.9
Requires-Dist: urllib3<3.0.0,>=2.1.0
Requires-Dist: python-dateutil>=2.8.2
Requires-Dist: pydantic>=2
Requires-Dist: typing-extensions>=4.7.1
Dynamic: author
